setup.py
smartc/__init__.py
smartc.egg-info/PKG-INFO
smartc.egg-info/SOURCES.txt
smartc.egg-info/dependency_links.txt
smartc.egg-info/not-zip-safe
smartc.egg-info/top_level.txt