Metadata-Version: 1.0
Name: smartc
Version: 0.0.1
Summary: Smart contracts reengineered
Home-page: UNKNOWN
Author: Guillem Borrell
Author-email: guillemborrell@gmail.com
License: UNKNOWN
Platform: UNKNOWN
